sim_web_visualizer/__init__.py
sim_web_visualizer/base_visualizer_client.py
sim_web_visualizer/isaac_visualizer_client.py
sim_web_visualizer/sapien_visualizer_client.py
sim_web_visualizer/assets/axis_geom/xyz_axis.mtl
sim_web_visualizer/assets/axis_geom/xyz_axis.obj
sim_web_visualizer/parser/__init__.py
sim_web_visualizer/parser/mesh_parser.py
sim_web_visualizer/parser/mjcf.py
sim_web_visualizer/parser/urdf.py
sim_web_visualizer/parser/yourdfpy.py
sim_web_visualizer/utils/__init__.py
sim_web_visualizer/utils/rotation_utils.py
sim_web_visualizer-0.6.0.dist-info/LICENSE
sim_web_visualizer-0.6.0.dist-info/METADATA
sim_web_visualizer-0.6.0.dist-info/WHEEL
sim_web_visualizer-0.6.0.dist-info/top_level.txt
sim_web_visualizer-0.6.0.dist-info/zip-safe
sim_web_visualizer-0.6.0.dist-info/RECORD
