Metadata-Version: 2.1
Name: sim-web-visualizer
Version: 0.6.0
Summary: Web based visualizer for simulators
Home-page: https://github.com/NVlabs/sim-web-visualizer
Author: Yuzhe Qin
Author-email: y1qin@ucsd.edu
Maintainer: Yuzhe Qin
Maintainer-email: y1qin@ucsd.edu
License: MIT
Classifier: Development Status :: 3 - Alpha
Classifier: Intended Audience :: Developers
Classifier: Intended Audience :: Science/Research
Classifier: License :: OSI Approved :: MIT License
Classifier: Natural Language :: English
Classifier: Programming Language :: Python :: 3
Classifier: Programming Language :: Python :: 3.6
Classifier: Programming Language :: Python :: 3.7
Classifier: Programming Language :: Python :: 3.8
Classifier: Programming Language :: Python :: 3.9
Classifier: Programming Language :: Python :: 3.10
Classifier: Topic :: Scientific/Engineering :: Artificial Intelligence
Requires-Python: >=3.6,<3.11
License-File: LICENSE
Requires-Dist: numpy <=1.23.0
Requires-Dist: numpy-quaternion
Requires-Dist: transforms3d
Requires-Dist: dm-control >=1.0.0
Requires-Dist: anytree
Requires-Dist: trimesh
Requires-Dist: pycollada
Requires-Dist: mujoco >=2.2.0
Requires-Dist: meshcat-sim-web-fork
Provides-Extra: isaacgym
Requires-Dist: hydra-core ; extra == 'isaacgym'
Requires-Dist: gym ==0.23.1 ; extra == 'isaacgym'
Requires-Dist: rl-games ; extra == 'isaacgym'
Requires-Dist: torch ; extra == 'isaacgym'
Requires-Dist: pyvirtualdisplay ; extra == 'isaacgym'
Requires-Dist: omegaconf ; extra == 'isaacgym'
Requires-Dist: jinja2 ; extra == 'isaacgym'
Provides-Extra: sapien
Requires-Dist: mani-skill2 ; extra == 'sapien'
